dataset_downloader/__init__.py
dataset_downloader/cli.py
dataset_downloader/downloader.py
dataset_downloader/urls.py
dataset_downloader-1.0.0.dist-info/LICENSE
dataset_downloader-1.0.0.dist-info/METADATA
dataset_downloader-1.0.0.dist-info/WHEEL
dataset_downloader-1.0.0.dist-info/entry_points.txt
dataset_downloader-1.0.0.dist-info/top_level.txt
dataset_downloader-1.0.0.dist-info/RECORD
