Metadata-Version: 2.1
Name: dataset-downloader
Version: 1.0.0
Summary: Tool to download large dataset from a list of url
Home-page: https://github.com/johnrazeur/dataset_downloader
Author: Clément Lafont
Author-email: lafont.clem@gmail.com
License: UNKNOWN
Platform: UNKNOWN
Classifier: Programming Language :: Python :: 3
Classifier: License :: OSI Approved :: MIT License
Classifier: Operating System :: OS Independent
Classifier: Topic :: Scientific/Engineering :: Artificial Intelligence
Requires-Dist: Click (==7.0)
Requires-Dist: requests (==2.20.0)
